taler_shared/__init__.py
taler_shared/api/__init__.py
taler_shared/api/api_client.py
taler_shared/api/parse_for_apis.py
taler_shared/environment/__init__.py
taler_shared/environment/load_env_variables.py
taler_shared/utils/__init__.py
taler_shared/utils/type_utils.py
taler_shared-0.2.1.dist-info/LICENSE
taler_shared-0.2.1.dist-info/METADATA
taler_shared-0.2.1.dist-info/WHEEL
taler_shared-0.2.1.dist-info/top_level.txt
taler_shared-0.2.1.dist-info/RECORD
