Metadata-Version: 2.1
Name: taler_shared
Version: 0.2.1
License-File: LICENSE
Requires-Dist: certifi>=2024.2.2
Requires-Dist: pydantic>=1.8.0
Requires-Dist: requests>=2.31.0
Requires-Dist: setuptools>=61.0.0
Requires-Dist: python-dotenv>=1.0.0
